ebbp/__init__.py
ebbp/add_ebb_estimate.py
ebbp/ebb_fit_estimate.py
ebbp/ebb_fit_mixture.py
ebbp/ebb_fit_prior.py
ebbp-0.1.dist-info/LICENSE
ebbp-0.1.dist-info/METADATA
ebbp-0.1.dist-info/WHEEL
ebbp-0.1.dist-info/top_level.txt
ebbp-0.1.dist-info/RECORD
