Metadata-Version: 2.1
Name: ebbp
Version: 0.1
Summary: Empirical Bayes for the Binomial in Python
Home-page: https://github.com/uttiyamaji/ebbp
Author: Uttiya Maji
Author-email: iuttiya@gmail.com
License: UNKNOWN
Platform: UNKNOWN
Classifier: Programming Language :: Python :: 3
Classifier: License :: OSI Approved :: MIT License
Classifier: Operating System :: OS Independent
Requires-Python: >=3.6
